__init__.py
comseg/__init__.py
comseg/clustering.py
comseg/dataset.py
comseg/dictionary.py
comseg/model.py
comseg/utils/__init__.py
comseg/utils/custom_louvain.py
comseg/utils/plot.py
comseg/utils/preprocessing.py
comseg/utils/utils_graph.py
ComSeg-1.8.5.dist-info/LICENSE
ComSeg-1.8.5.dist-info/METADATA
ComSeg-1.8.5.dist-info/WHEEL
ComSeg-1.8.5.dist-info/top_level.txt
ComSeg-1.8.5.dist-info/RECORD
